edgar/__init__.py
edgar/main.py
python_edgar-3.1.3.data/scripts/run.py
python_edgar-3.1.3.dist-info/AUTHORS
python_edgar-3.1.3.dist-info/LICENSE
python_edgar-3.1.3.dist-info/METADATA
python_edgar-3.1.3.dist-info/WHEEL
python_edgar-3.1.3.dist-info/top_level.txt
python_edgar-3.1.3.dist-info/RECORD
