Metadata-Version: 2.1
Name: python-edgar
Version: 3.1.3
Summary: Download the SEC fillings index from EDGAR since 1993
Home-page: https://github.com/edouardswiac/python-edgar
Author: Edouard Swiac
Author-email: edouard.swiac@gmail.com
License: MIT
Project-URL: Bug Tracker, https://github.com/edouardswiac/python-edgar/issues
Project-URL: Documentation, https://github.com/edouardswiac/python-edgar/blob/master/README.md
Project-URL: Source Code, https://github.com/edouardswiac/python-edgar/
Keywords: edgar sec filings 10k 10q 13d 8k
Platform: UNKNOWN
Classifier: Development Status :: 5 - Production/Stable
Classifier: License :: OSI Approved :: MIT License
Classifier: Intended Audience :: Developers
Classifier: Intended Audience :: Information Technology
Classifier: Intended Audience :: Financial and Insurance Industry
Classifier: Operating System :: OS Independent
Classifier: Programming Language :: Python :: 3
Classifier: Topic :: Office/Business :: Financial
Classifier: Topic :: Office/Business :: Financial :: Investment
License-File: LICENSE
License-File: AUTHORS
